lcn/__init__.py
lcn-0.0.1.dist-info/licenses/LICENSE
lcn-0.0.1.dist-info/METADATA
lcn-0.0.1.dist-info/WHEEL
lcn-0.0.1.dist-info/entry_points.txt
lcn-0.0.1.dist-info/top_level.txt
lcn-0.0.1.dist-info/RECORD
